{
  "info": {
    "name": "Bareeq Marketplace (Sprint 3)",
    "description": "Marketplace endpoints — Sprint 3 + Sprint 4 bookings.\n\nUsage:\n1. Import this collection AND the matching `bareeq-api.postman_environment.json` environment file.\n2. Select the 'Bareeq Local' environment in the top-right.\n3. Run the folders top-to-bottom (or use the Runner on the whole collection).\n   - Each Create endpoint auto-captures its ID + tokens into env variables.\n   - Customer + SP signup capture the dev-mode OTP into env automatically.\n\nFolder layout:\n  00 — Admin Login                captures adminAccessToken\n  01 — Customer Auth              signup → verify (auto-login) → password reset\n  02 — Service Provider Auth      same shape as Customer Auth\n  03 — Admin Service Categories   CRUD (requires admin token from folder 00)\n  04 — Admin Services             CRUD + commission + nested subcategories\n  05 — Customer Home              browse / filter / search / detail\n  06 — Customer Profile           GET / PATCH / change-password\n  07 — Service Provider Profile   GET / PATCH / change-password\n  08 — Admin Customers            list / detail / block-unblock\n  09 — Admin Service Providers    list / detail / block-unblock / KYC review\n  10 — Customer Bookings          create / list / detail / cancel\n  11 — SP Bookings                pool / accept / list / start / complete\n  12 — Admin Bookings             list / detail (read-only oversight)\n\nFRD references: Service Management §1.1–§1.3, §2.1–§2.3, §3.2–§3.4.",
    "schema": "https://schema.getpostman.com/json/collection/v2.1.0/collection.json"
  },
  "item": [
    {
      "name": "00 — Admin Login (for admin folders)",
      "item": [
        {
          "name": "POST /auth/web/login (admin) — captures adminAccessToken",
          "event": [
            {
              "listen": "test",
              "script": {
                "type": "text/javascript",
                "exec": [
                  "const res = pm.response.json();",
                  "if (res.success && res.data) {",
                  "  pm.environment.set('adminAccessToken', res.data.accessToken);",
                  "  console.log('Admin token saved.');",
                  "}"
                ]
              }
            }
          ],
          "request": {
            "method": "POST",
            "header": [{ "key": "Content-Type", "value": "application/json" }],
            "url": {
              "raw": "{{baseUrl}}/auth/web/login",
              "host": ["{{baseUrl}}"],
              "path": ["auth", "web", "login"]
            },
            "body": {
              "mode": "raw",
              "raw": "{\n  \"identifier\": \"{{adminEmail}}\",\n  \"password\": \"{{adminPassword}}\"\n}"
            }
          }
        }
      ]
    },
    {
      "name": "01 — Customer Auth (FRD §1.1)",
      "item": [
        {
          "name": "POST /auth/customer/signup — captures customerSignupOtp",
          "event": [
            {
              "listen": "test",
              "script": {
                "type": "text/javascript",
                "exec": [
                  "const res = pm.response.json();",
                  "if (res.success && res.data && res.data.otp) {",
                  "  pm.environment.set('customerSignupOtp', res.data.otp);",
                  "  console.log('Customer signup OTP captured (dev mode only):', res.data.otp);",
                  "}"
                ]
              }
            }
          ],
          "request": {
            "method": "POST",
            "header": [{ "key": "Content-Type", "value": "application/json" }],
            "url": {
              "raw": "{{baseUrl}}/auth/customer/signup",
              "host": ["{{baseUrl}}"],
              "path": ["auth", "customer", "signup"]
            },
            "body": {
              "mode": "raw",
              "raw": "{\n  \"email\": \"{{customerEmail}}\",\n  \"password\": \"{{customerPassword}}\",\n  \"nameAr\": \"عميل اختبار\",\n  \"nameEn\": \"Test Customer\",\n  \"phone\": \"+966501112222\"\n}"
            },
            "description": "Step 1 of signup. Validates the email isn't already registered (any role) and issues an email OTP. The User row is NOT created yet.\n\nIn dev (NODE_ENV != production) the response includes the plaintext OTP for testing."
          }
        },
        {
          "name": "POST /auth/customer/signup/verify — captures customerAccessToken",
          "event": [
            {
              "listen": "test",
              "script": {
                "type": "text/javascript",
                "exec": [
                  "const res = pm.response.json();",
                  "if (res.success && res.data && res.data.accessToken) {",
                  "  pm.environment.set('customerAccessToken', res.data.accessToken);",
                  "  pm.environment.set('customerRefreshToken', res.data.refreshToken);",
                  "  pm.environment.set('customerId', res.data.user.id);",
                  "  console.log('Customer logged in.');",
                  "}"
                ]
              }
            }
          ],
          "request": {
            "method": "POST",
            "header": [{ "key": "Content-Type", "value": "application/json" }],
            "url": {
              "raw": "{{baseUrl}}/auth/customer/signup/verify",
              "host": ["{{baseUrl}}"],
              "path": ["auth", "customer", "signup", "verify"]
            },
            "body": {
              "mode": "raw",
              "raw": "{\n  \"email\": \"{{customerEmail}}\",\n  \"password\": \"{{customerPassword}}\",\n  \"nameAr\": \"عميل اختبار\",\n  \"nameEn\": \"Test Customer\",\n  \"phone\": \"+966501112222\",\n  \"otp\": \"{{customerSignupOtp}}\"\n}"
            },
            "description": "Step 2: verifies the OTP and atomically creates the User + Customer satellite. On success auto-logs in and returns access + refresh tokens (response matches /auth/mobile/login)."
          }
        },
        {
          "name": "POST /auth/customer/password-reset/request — captures customerResetOtp",
          "event": [
            {
              "listen": "test",
              "script": {
                "type": "text/javascript",
                "exec": [
                  "const res = pm.response.json();",
                  "if (res.success && res.data && res.data.otp) {",
                  "  pm.environment.set('customerResetOtp', res.data.otp);",
                  "}"
                ]
              }
            }
          ],
          "request": {
            "method": "POST",
            "header": [{ "key": "Content-Type", "value": "application/json" }],
            "url": {
              "raw": "{{baseUrl}}/auth/customer/password-reset/request",
              "host": ["{{baseUrl}}"],
              "path": ["auth", "customer", "password-reset", "request"]
            },
            "body": {
              "mode": "raw",
              "raw": "{\n  \"email\": \"{{customerEmail}}\"\n}"
            },
            "description": "Anti-enumeration: response shape is the same whether or not the email exists in production. In dev, the OTP only appears when the email is real — that's how we capture it here."
          }
        },
        {
          "name": "POST /auth/customer/password-reset/confirm",
          "request": {
            "method": "POST",
            "header": [{ "key": "Content-Type", "value": "application/json" }],
            "url": {
              "raw": "{{baseUrl}}/auth/customer/password-reset/confirm",
              "host": ["{{baseUrl}}"],
              "path": ["auth", "customer", "password-reset", "confirm"]
            },
            "body": {
              "mode": "raw",
              "raw": "{\n  \"email\": \"{{customerEmail}}\",\n  \"otp\": \"{{customerResetOtp}}\",\n  \"newPassword\": \"newpass123\"\n}"
            },
            "description": "Verifies the reset OTP, hashes the new password, and revokes every active refresh token for the account so any compromised device is logged out."
          }
        },
        {
          "name": "POST /auth/mobile/login (as customer) — captures customerAccessToken",
          "event": [
            {
              "listen": "test",
              "script": {
                "type": "text/javascript",
                "exec": [
                  "const res = pm.response.json();",
                  "if (res.success && res.data && res.data.accessToken) {",
                  "  pm.environment.set('customerAccessToken', res.data.accessToken);",
                  "}"
                ]
              }
            }
          ],
          "request": {
            "method": "POST",
            "header": [{ "key": "Content-Type", "value": "application/json" }],
            "url": {
              "raw": "{{baseUrl}}/auth/mobile/login",
              "host": ["{{baseUrl}}"],
              "path": ["auth", "mobile", "login"]
            },
            "body": {
              "mode": "raw",
              "raw": "{\n  \"identifier\": \"{{customerEmail}}\",\n  \"password\": \"{{customerPassword}}\"\n}"
            },
            "description": "Customers log in via the SAME mobile-login endpoint as supervisors. The role on the User row controls the experience. ROLE_CLIENT_MAP enforces that CUSTOMER cannot log in from the web surface."
          }
        }
      ]
    },
    {
      "name": "02 — Service Provider Auth (FRD §2.1)",
      "item": [
        {
          "name": "POST /auth/service-provider/signup — captures spSignupOtp",
          "event": [
            {
              "listen": "test",
              "script": {
                "type": "text/javascript",
                "exec": [
                  "const res = pm.response.json();",
                  "if (res.success && res.data && res.data.otp) {",
                  "  pm.environment.set('spSignupOtp', res.data.otp);",
                  "}"
                ]
              }
            }
          ],
          "request": {
            "method": "POST",
            "header": [{ "key": "Content-Type", "value": "application/json" }],
            "url": {
              "raw": "{{baseUrl}}/auth/service-provider/signup",
              "host": ["{{baseUrl}}"],
              "path": ["auth", "service-provider", "signup"]
            },
            "body": {
              "mode": "raw",
              "raw": "{\n  \"email\": \"{{spEmail}}\",\n  \"password\": \"{{spPassword}}\",\n  \"nameAr\": \"مزود خدمة\",\n  \"nameEn\": \"Test SP\",\n  \"phone\": \"+966503334444\",\n  \"bio\": \"كهربائي بخبرة 10 سنوات\"\n}"
            },
            "description": "Same flow as Customer signup. `bio` is the only SP-only field; it's optional and can be set later via profile-update endpoints."
          }
        },
        {
          "name": "POST /auth/service-provider/signup/verify — captures spAccessToken",
          "event": [
            {
              "listen": "test",
              "script": {
                "type": "text/javascript",
                "exec": [
                  "const res = pm.response.json();",
                  "if (res.success && res.data && res.data.accessToken) {",
                  "  pm.environment.set('spAccessToken', res.data.accessToken);",
                  "  pm.environment.set('spId', res.data.user.id);",
                  "}"
                ]
              }
            }
          ],
          "request": {
            "method": "POST",
            "header": [{ "key": "Content-Type", "value": "application/json" }],
            "url": {
              "raw": "{{baseUrl}}/auth/service-provider/signup/verify",
              "host": ["{{baseUrl}}"],
              "path": ["auth", "service-provider", "signup", "verify"]
            },
            "body": {
              "mode": "raw",
              "raw": "{\n  \"email\": \"{{spEmail}}\",\n  \"password\": \"{{spPassword}}\",\n  \"nameAr\": \"مزود خدمة\",\n  \"nameEn\": \"Test SP\",\n  \"phone\": \"+966503334444\",\n  \"bio\": \"كهربائي بخبرة 10 سنوات\",\n  \"otp\": \"{{spSignupOtp}}\"\n}"
            },
            "description": "Creates User (role=SERVICE_PROVIDER) + ServiceProvider satellite (with bio, kycStatus=NOT_SUBMITTED default). Auto-login returns mobile tokens."
          }
        },
        {
          "name": "POST /auth/service-provider/password-reset/request — captures spResetOtp",
          "event": [
            {
              "listen": "test",
              "script": {
                "type": "text/javascript",
                "exec": [
                  "const res = pm.response.json();",
                  "if (res.success && res.data && res.data.otp) {",
                  "  pm.environment.set('spResetOtp', res.data.otp);",
                  "}"
                ]
              }
            }
          ],
          "request": {
            "method": "POST",
            "header": [{ "key": "Content-Type", "value": "application/json" }],
            "url": {
              "raw": "{{baseUrl}}/auth/service-provider/password-reset/request",
              "host": ["{{baseUrl}}"],
              "path": ["auth", "service-provider", "password-reset", "request"]
            },
            "body": {
              "mode": "raw",
              "raw": "{\n  \"email\": \"{{spEmail}}\"\n}"
            }
          }
        },
        {
          "name": "POST /auth/service-provider/password-reset/confirm",
          "request": {
            "method": "POST",
            "header": [{ "key": "Content-Type", "value": "application/json" }],
            "url": {
              "raw": "{{baseUrl}}/auth/service-provider/password-reset/confirm",
              "host": ["{{baseUrl}}"],
              "path": ["auth", "service-provider", "password-reset", "confirm"]
            },
            "body": {
              "mode": "raw",
              "raw": "{\n  \"email\": \"{{spEmail}}\",\n  \"otp\": \"{{spResetOtp}}\",\n  \"newPassword\": \"newsppass123\"\n}"
            }
          }
        }
      ]
    },
    {
      "name": "03 — Admin Service Categories (FRD §3.4)",
      "item": [
        {
          "name": "POST /admin/service-categories — captures serviceCategoryId",
          "event": [
            {
              "listen": "test",
              "script": {
                "type": "text/javascript",
                "exec": [
                  "const res = pm.response.json();",
                  "if (res.success && res.data) {",
                  "  pm.environment.set('serviceCategoryId', res.data.id);",
                  "}"
                ]
              }
            }
          ],
          "request": {
            "method": "POST",
            "header": [
              { "key": "Content-Type", "value": "application/json" },
              { "key": "Authorization", "value": "Bearer {{adminAccessToken}}" }
            ],
            "url": {
              "raw": "{{baseUrl}}/admin/service-categories",
              "host": ["{{baseUrl}}"],
              "path": ["admin", "service-categories"]
            },
            "body": {
              "mode": "raw",
              "raw": "{\n  \"titleAr\": \"خدمات منزلية\",\n  \"titleEn\": \"Home Services\",\n  \"iconUrl\": \"https://example.com/home.png\",\n  \"sortOrder\": 1\n}"
            }
          }
        },
        {
          "name": "GET /admin/service-categories (list + filters)",
          "request": {
            "method": "GET",
            "header": [{ "key": "Authorization", "value": "Bearer {{adminAccessToken}}" }],
            "url": {
              "raw": "{{baseUrl}}/admin/service-categories?page=1&limit=20&sort=sortOrder",
              "host": ["{{baseUrl}}"],
              "path": ["admin", "service-categories"],
              "query": [
                { "key": "page", "value": "1" },
                { "key": "limit", "value": "20" },
                { "key": "q", "value": "", "disabled": true },
                { "key": "isActive", "value": "true", "disabled": true },
                { "key": "sort", "value": "sortOrder" }
              ]
            }
          }
        },
        {
          "name": "GET /admin/service-categories/:id",
          "request": {
            "method": "GET",
            "header": [{ "key": "Authorization", "value": "Bearer {{adminAccessToken}}" }],
            "url": {
              "raw": "{{baseUrl}}/admin/service-categories/{{serviceCategoryId}}",
              "host": ["{{baseUrl}}"],
              "path": ["admin", "service-categories", "{{serviceCategoryId}}"]
            }
          }
        },
        {
          "name": "PATCH /admin/service-categories/:id",
          "request": {
            "method": "PATCH",
            "header": [
              { "key": "Content-Type", "value": "application/json" },
              { "key": "Authorization", "value": "Bearer {{adminAccessToken}}" }
            ],
            "url": {
              "raw": "{{baseUrl}}/admin/service-categories/{{serviceCategoryId}}",
              "host": ["{{baseUrl}}"],
              "path": ["admin", "service-categories", "{{serviceCategoryId}}"]
            },
            "body": {
              "mode": "raw",
              "raw": "{\n  \"titleEn\": \"Home Services (Updated)\",\n  \"sortOrder\": 5\n}"
            }
          }
        },
        {
          "name": "DELETE /admin/service-categories/:id",
          "request": {
            "method": "DELETE",
            "header": [{ "key": "Authorization", "value": "Bearer {{adminAccessToken}}" }],
            "url": {
              "raw": "{{baseUrl}}/admin/service-categories/{{serviceCategoryId}}",
              "host": ["{{baseUrl}}"],
              "path": ["admin", "service-categories", "{{serviceCategoryId}}"]
            },
            "description": "Blocked with 409 if any active Service still references this category. Move/delete those Services first."
          }
        }
      ]
    },
    {
      "name": "04 — Admin Services (FRD §3.4.1)",
      "item": [
        {
          "name": "POST /admin/services (with subcategories) — captures serviceId",
          "event": [
            {
              "listen": "test",
              "script": {
                "type": "text/javascript",
                "exec": [
                  "const res = pm.response.json();",
                  "if (res.success && res.data) {",
                  "  pm.environment.set('serviceId', res.data.id);",
                  "  console.log('Service created. totalCost =', res.data.totalCost);",
                  "}"
                ]
              }
            }
          ],
          "request": {
            "method": "POST",
            "header": [
              { "key": "Content-Type", "value": "application/json" },
              { "key": "Authorization", "value": "Bearer {{adminAccessToken}}" }
            ],
            "url": {
              "raw": "{{baseUrl}}/admin/services",
              "host": ["{{baseUrl}}"],
              "path": ["admin", "services"]
            },
            "body": {
              "mode": "raw",
              "raw": "{\n  \"categoryId\": \"{{serviceCategoryId}}\",\n  \"titleAr\": \"سباكة\",\n  \"titleEn\": \"Plumbing\",\n  \"descriptionAr\": \"خدمات سباكة منزلية\",\n  \"descriptionEn\": \"Residential plumbing services\",\n  \"imageUrl\": \"https://example.com/plumbing.png\",\n  \"commissionRate\": 10,\n  \"subcategories\": [\n    { \"titleAr\": \"تسليك مجاري\", \"titleEn\": \"Drain cleaning\", \"cost\": 100 },\n    { \"titleAr\": \"إصلاح أنابيب\", \"titleEn\": \"Pipe repair\", \"cost\": 200 },\n    { \"titleAr\": \"تركيب مرحاض\", \"titleEn\": \"Toilet install\", \"cost\": 150 }\n  ]\n}"
            },
            "description": "Creates the Service + its subcategories atomically. The response's totalCost is the sum of all subcategory costs (the 'default' service cost the customer sees)."
          }
        },
        {
          "name": "GET /admin/services (list + filters)",
          "request": {
            "method": "GET",
            "header": [{ "key": "Authorization", "value": "Bearer {{adminAccessToken}}" }],
            "url": {
              "raw": "{{baseUrl}}/admin/services?page=1&limit=20&sort=sortOrder",
              "host": ["{{baseUrl}}"],
              "path": ["admin", "services"],
              "query": [
                { "key": "page", "value": "1" },
                { "key": "limit", "value": "20" },
                { "key": "q", "value": "", "disabled": true },
                { "key": "categoryId", "value": "{{serviceCategoryId}}", "disabled": true },
                { "key": "isActive", "value": "true", "disabled": true },
                { "key": "sort", "value": "sortOrder" }
              ]
            }
          }
        },
        {
          "name": "GET /admin/services/:id (with subcategories + totalCost)",
          "request": {
            "method": "GET",
            "header": [{ "key": "Authorization", "value": "Bearer {{adminAccessToken}}" }],
            "url": {
              "raw": "{{baseUrl}}/admin/services/{{serviceId}}",
              "host": ["{{baseUrl}}"],
              "path": ["admin", "services", "{{serviceId}}"]
            }
          }
        },
        {
          "name": "PATCH /admin/services/:id (replace-all subcategories)",
          "request": {
            "method": "PATCH",
            "header": [
              { "key": "Content-Type", "value": "application/json" },
              { "key": "Authorization", "value": "Bearer {{adminAccessToken}}" }
            ],
            "url": {
              "raw": "{{baseUrl}}/admin/services/{{serviceId}}",
              "host": ["{{baseUrl}}"],
              "path": ["admin", "services", "{{serviceId}}"]
            },
            "body": {
              "mode": "raw",
              "raw": "{\n  \"titleEn\": \"Plumbing (Updated)\",\n  \"subcategories\": [\n    { \"titleAr\": \"تسليك مجاري\", \"titleEn\": \"Drain cleaning\", \"cost\": 120 },\n    { \"titleAr\": \"إصلاح أنابيب\", \"titleEn\": \"Pipe repair\", \"cost\": 220 },\n    { \"titleAr\": \"تركيب سخان\", \"titleEn\": \"Water heater install\", \"cost\": 300 }\n  ]\n}"
            },
            "description": "If `subcategories` is in the body, it REPLACES the existing list (soft-delete old + create new, preserving audit trail). If omitted, subcategories are left untouched."
          }
        },
        {
          "name": "PATCH /admin/services/:id/commission (FRD §3.4.1.5)",
          "request": {
            "method": "PATCH",
            "header": [
              { "key": "Content-Type", "value": "application/json" },
              { "key": "Authorization", "value": "Bearer {{adminAccessToken}}" }
            ],
            "url": {
              "raw": "{{baseUrl}}/admin/services/{{serviceId}}/commission",
              "host": ["{{baseUrl}}"],
              "path": ["admin", "services", "{{serviceId}}", "commission"]
            },
            "body": {
              "mode": "raw",
              "raw": "{\n  \"commissionRate\": 15.5\n}"
            }
          }
        },
        {
          "name": "DELETE /admin/services/:id (cascades to subcategories)",
          "request": {
            "method": "DELETE",
            "header": [{ "key": "Authorization", "value": "Bearer {{adminAccessToken}}" }],
            "url": {
              "raw": "{{baseUrl}}/admin/services/{{serviceId}}",
              "host": ["{{baseUrl}}"],
              "path": ["admin", "services", "{{serviceId}}"]
            }
          }
        }
      ]
    },
    {
      "name": "05 — Customer Home (FRD §1.2)",
      "item": [
        {
          "name": "GET /customer/home/categories",
          "request": {
            "method": "GET",
            "header": [{ "key": "Authorization", "value": "Bearer {{customerAccessToken}}" }],
            "url": {
              "raw": "{{baseUrl}}/customer/home/categories?page=1&limit=20",
              "host": ["{{baseUrl}}"],
              "path": ["customer", "home", "categories"],
              "query": [
                { "key": "page", "value": "1" },
                { "key": "limit", "value": "20" }
              ]
            },
            "description": "FRD §1.2.3 — returns active categories sorted by sortOrder. Minimal card payload (id, titleAr/En, iconUrl)."
          }
        },
        {
          "name": "GET /customer/home/services (browse + filter + search)",
          "request": {
            "method": "GET",
            "header": [{ "key": "Authorization", "value": "Bearer {{customerAccessToken}}" }],
            "url": {
              "raw": "{{baseUrl}}/customer/home/services?page=1&limit=20&sort=sortOrder",
              "host": ["{{baseUrl}}"],
              "path": ["customer", "home", "services"],
              "query": [
                { "key": "page", "value": "1" },
                { "key": "limit", "value": "20" },
                { "key": "q", "value": "", "disabled": true },
                { "key": "categoryId", "value": "{{serviceCategoryId}}", "disabled": true },
                { "key": "minRating", "value": "3.5", "disabled": true },
                { "key": "maxRating", "value": "5", "disabled": true },
                { "key": "minCost", "value": "100", "disabled": true },
                { "key": "maxCost", "value": "500", "disabled": true },
                { "key": "sort", "value": "sortOrder", "description": "sortOrder | rating | newest | priceAsc | priceDesc" }
              ]
            },
            "description": "FRD §1.2.1, §1.2.4, §1.2.5. Cost-range filter (`minCost` / `maxCost`) is applied in-memory after fetch because totalCost = SUM of subcategory costs (not a column). Each card carries totalCost + rating + image."
          }
        },
        {
          "name": "GET /customer/home/services/:id (detail with subcategories)",
          "request": {
            "method": "GET",
            "header": [{ "key": "Authorization", "value": "Bearer {{customerAccessToken}}" }],
            "url": {
              "raw": "{{baseUrl}}/customer/home/services/{{serviceId}}",
              "host": ["{{baseUrl}}"],
              "path": ["customer", "home", "services", "{{serviceId}}"]
            },
            "description": "FRD §1.2.2. Returns the full service, every active subcategory (with cost), plus totalCost (sum of all subcategories — the 'default-all-selected' price). The client subtracts costs as the user un-picks subcategories."
          }
        }
      ]
    },
    {
      "name": "06 — Customer Profile (FRD §1.1)",
      "item": [
        {
          "name": "GET /customer/profile",
          "request": {
            "method": "GET",
            "header": [{ "key": "Authorization", "value": "Bearer {{customerAccessToken}}" }],
            "url": {
              "raw": "{{baseUrl}}/customer/profile",
              "host": ["{{baseUrl}}"],
              "path": ["customer", "profile"]
            },
            "description": "Returns the joined User + Customer satellite (name, phone, email, profile picture, walletBalance). Wallet activity itself is Sprint 4."
          }
        },
        {
          "name": "PATCH /customer/profile",
          "request": {
            "method": "PATCH",
            "header": [
              { "key": "Content-Type", "value": "application/json" },
              { "key": "Authorization", "value": "Bearer {{customerAccessToken}}" }
            ],
            "url": {
              "raw": "{{baseUrl}}/customer/profile",
              "host": ["{{baseUrl}}"],
              "path": ["customer", "profile"]
            },
            "body": {
              "mode": "raw",
              "raw": "{\n  \"nameEn\": \"Updated Name\",\n  \"phone\": \"+966509998877\",\n  \"profilePicture\": \"https://example.com/avatar.png\"\n}"
            },
            "description": "Partial update — only fields in the body are touched. Email is NOT editable here (would need re-verification). Empty body returns 400."
          }
        },
        {
          "name": "POST /customer/profile/change-password",
          "request": {
            "method": "POST",
            "header": [
              { "key": "Content-Type", "value": "application/json" },
              { "key": "Authorization", "value": "Bearer {{customerAccessToken}}" }
            ],
            "url": {
              "raw": "{{baseUrl}}/customer/profile/change-password",
              "host": ["{{baseUrl}}"],
              "path": ["customer", "profile", "change-password"]
            },
            "body": {
              "mode": "raw",
              "raw": "{\n  \"currentPassword\": \"{{customerPassword}}\",\n  \"newPassword\": \"newpassXYZ123\"\n}"
            },
            "description": "Requires the current password (not just the access token). On success, every active refresh token is revoked — all devices logged out. Same password as current is rejected (400)."
          }
        }
      ]
    },
    {
      "name": "07 — Service Provider Profile (FRD §2.1)",
      "item": [
        {
          "name": "GET /service-provider/profile",
          "request": {
            "method": "GET",
            "header": [{ "key": "Authorization", "value": "Bearer {{spAccessToken}}" }],
            "url": {
              "raw": "{{baseUrl}}/service-provider/profile",
              "host": ["{{baseUrl}}"],
              "path": ["service-provider", "profile"]
            },
            "description": "Returns User + ServiceProvider satellite — adds bio, isVerified, kycStatus, walletBalance, ratingAverage, ratingCount on top of the base fields."
          }
        },
        {
          "name": "PATCH /service-provider/profile",
          "request": {
            "method": "PATCH",
            "header": [
              { "key": "Content-Type", "value": "application/json" },
              { "key": "Authorization", "value": "Bearer {{spAccessToken}}" }
            ],
            "url": {
              "raw": "{{baseUrl}}/service-provider/profile",
              "host": ["{{baseUrl}}"],
              "path": ["service-provider", "profile"]
            },
            "body": {
              "mode": "raw",
              "raw": "{\n  \"nameEn\": \"Master Electrician\",\n  \"bio\": \"كهربائي بخبرة 15 سنة\",\n  \"profilePicture\": \"https://example.com/sp-avatar.png\"\n}"
            },
            "description": "Partial update. KYC document upload is NOT here — it lives in a separate /kyc/submit endpoint (Sprint 4) that handles file upload + sets kycStatus = PENDING."
          }
        },
        {
          "name": "POST /service-provider/profile/change-password",
          "request": {
            "method": "POST",
            "header": [
              { "key": "Content-Type", "value": "application/json" },
              { "key": "Authorization", "value": "Bearer {{spAccessToken}}" }
            ],
            "url": {
              "raw": "{{baseUrl}}/service-provider/profile/change-password",
              "host": ["{{baseUrl}}"],
              "path": ["service-provider", "profile", "change-password"]
            },
            "body": {
              "mode": "raw",
              "raw": "{\n  \"currentPassword\": \"{{spPassword}}\",\n  \"newPassword\": \"newspXYZ456\"\n}"
            }
          }
        }
      ]
    },
    {
      "name": "08 — Admin Customers (FRD §3.2.1)",
      "item": [
        {
          "name": "GET /admin/customers (list + filters)",
          "request": {
            "method": "GET",
            "header": [{ "key": "Authorization", "value": "Bearer {{adminAccessToken}}" }],
            "url": {
              "raw": "{{baseUrl}}/admin/customers?page=1&limit=20&sort=newest",
              "host": ["{{baseUrl}}"],
              "path": ["admin", "customers"],
              "query": [
                { "key": "page", "value": "1" },
                { "key": "limit", "value": "20" },
                { "key": "q", "value": "", "disabled": true, "description": "search email/phone/name" },
                { "key": "status", "value": "ENABLED", "disabled": true, "description": "ENABLED | BLOCKED" },
                { "key": "sort", "value": "newest", "description": "newest | oldest | name" }
              ]
            }
          }
        },
        {
          "name": "GET /admin/customers/:id",
          "request": {
            "method": "GET",
            "header": [{ "key": "Authorization", "value": "Bearer {{adminAccessToken}}" }],
            "url": {
              "raw": "{{baseUrl}}/admin/customers/{{customerId}}",
              "host": ["{{baseUrl}}"],
              "path": ["admin", "customers", "{{customerId}}"]
            }
          }
        },
        {
          "name": "PATCH /admin/customers/:id/status (block/unblock)",
          "request": {
            "method": "PATCH",
            "header": [
              { "key": "Content-Type", "value": "application/json" },
              { "key": "Authorization", "value": "Bearer {{adminAccessToken}}" }
            ],
            "url": {
              "raw": "{{baseUrl}}/admin/customers/{{customerId}}/status",
              "host": ["{{baseUrl}}"],
              "path": ["admin", "customers", "{{customerId}}", "status"]
            },
            "body": {
              "mode": "raw",
              "raw": "{\n  \"status\": \"BLOCKED\",\n  \"reason\": \"Suspicious activity (audit only)\"\n}"
            },
            "description": "Block (BLOCKED) revokes every active refresh token + bars login. Unblock (ENABLED) is idempotent — no token action. The `reason` is logged for audit; will surface in customer notifications when those ship in Sprint 4."
          }
        }
      ]
    },
    {
      "name": "09 — Admin Service Providers (FRD §3.2.2 + §2.1)",
      "item": [
        {
          "name": "GET /admin/service-providers (list + filters)",
          "request": {
            "method": "GET",
            "header": [{ "key": "Authorization", "value": "Bearer {{adminAccessToken}}" }],
            "url": {
              "raw": "{{baseUrl}}/admin/service-providers?page=1&limit=20&sort=newest",
              "host": ["{{baseUrl}}"],
              "path": ["admin", "service-providers"],
              "query": [
                { "key": "page", "value": "1" },
                { "key": "limit", "value": "20" },
                { "key": "q", "value": "", "disabled": true },
                { "key": "status", "value": "ENABLED", "disabled": true },
                { "key": "kycStatus", "value": "PENDING", "disabled": true, "description": "NOT_SUBMITTED | PENDING | APPROVED | REJECTED" },
                { "key": "isVerified", "value": "true", "disabled": true },
                { "key": "sort", "value": "newest", "description": "newest | oldest | name | rating | pendingFirst" }
              ]
            },
            "description": "Use `sort=pendingFirst` to surface SPs awaiting KYC review at the top of the list."
          }
        },
        {
          "name": "GET /admin/service-providers/:id",
          "request": {
            "method": "GET",
            "header": [{ "key": "Authorization", "value": "Bearer {{adminAccessToken}}" }],
            "url": {
              "raw": "{{baseUrl}}/admin/service-providers/{{spId}}",
              "host": ["{{baseUrl}}"],
              "path": ["admin", "service-providers", "{{spId}}"]
            }
          }
        },
        {
          "name": "PATCH /admin/service-providers/:id/status (block/unblock)",
          "request": {
            "method": "PATCH",
            "header": [
              { "key": "Content-Type", "value": "application/json" },
              { "key": "Authorization", "value": "Bearer {{adminAccessToken}}" }
            ],
            "url": {
              "raw": "{{baseUrl}}/admin/service-providers/{{spId}}/status",
              "host": ["{{baseUrl}}"],
              "path": ["admin", "service-providers", "{{spId}}", "status"]
            },
            "body": {
              "mode": "raw",
              "raw": "{\n  \"status\": \"BLOCKED\",\n  \"reason\": \"Multiple customer complaints (audit only)\"\n}"
            }
          }
        },
        {
          "name": "PATCH /admin/service-providers/:id/kyc (approve/reject)",
          "request": {
            "method": "PATCH",
            "header": [
              { "key": "Content-Type", "value": "application/json" },
              { "key": "Authorization", "value": "Bearer {{adminAccessToken}}" }
            ],
            "url": {
              "raw": "{{baseUrl}}/admin/service-providers/{{spId}}/kyc",
              "host": ["{{baseUrl}}"],
              "path": ["admin", "service-providers", "{{spId}}", "kyc"]
            },
            "body": {
              "mode": "raw",
              "raw": "{\n  \"decision\": \"APPROVED\",\n  \"notes\": \"All docs valid\"\n}"
            },
            "description": "APPROVED → sets kycStatus=APPROVED + isVerified=true + verifiedAt=now. REJECTED → kycStatus=REJECTED + isVerified=false + verifiedAt=null (clears any prior approval). `notes` is audit-only for now; will go into the SP's KYC-result notification in Sprint 4."
          }
        }
      ]
    },
    {
      "name": "10 — Customer Bookings (FRD §1.3)",
      "item": [
        {
          "name": "POST /customer/bookings (create) — captures bookingId",
          "event": [
            {
              "listen": "test",
              "script": {
                "type": "text/javascript",
                "exec": [
                  "const res = pm.response.json();",
                  "if (res.success && res.data) {",
                  "  pm.environment.set('bookingId', res.data.id);",
                  "  console.log('Booking created — total:', res.data.totalCost);",
                  "}"
                ]
              }
            }
          ],
          "request": {
            "method": "POST",
            "header": [
              { "key": "Content-Type", "value": "application/json" },
              { "key": "Authorization", "value": "Bearer {{customerAccessToken}}" }
            ],
            "url": {
              "raw": "{{baseUrl}}/customer/bookings",
              "host": ["{{baseUrl}}"],
              "path": ["customer", "bookings"]
            },
            "body": {
              "mode": "raw",
              "raw": "{\n  \"serviceId\": \"{{serviceId}}\",\n  \"subcategoryIds\": [\n    \"{{subcategoryId1}}\",\n    \"{{subcategoryId2}}\"\n  ],\n  \"description\": \"حاجة عاجلة\",\n  \"locationAddress\": \"الرياض - الصحافة\",\n  \"locationLat\": 24.7136,\n  \"locationLng\": 46.6753,\n  \"scheduledDate\": \"2026-12-01T10:00:00.000Z\",\n  \"paymentMethod\": \"CASH\"\n}"
            },
            "description": "totalCost is computed server-side as the SUM of cost across the selected subcategories. All subcategoryIds must belong to the chosen service.\n\nMVP only supports `CASH`; WALLET / ONLINE are rejected with 400 until Sprint 4 payment integration."
          }
        },
        {
          "name": "GET /customer/bookings (list own + filter)",
          "request": {
            "method": "GET",
            "header": [{ "key": "Authorization", "value": "Bearer {{customerAccessToken}}" }],
            "url": {
              "raw": "{{baseUrl}}/customer/bookings?page=1&limit=20&sort=newest",
              "host": ["{{baseUrl}}"],
              "path": ["customer", "bookings"],
              "query": [
                { "key": "page", "value": "1" },
                { "key": "limit", "value": "20" },
                { "key": "status", "value": "PENDING", "disabled": true, "description": "PENDING | APPROVED | IN_PROGRESS | COMPLETED | CANCELLED | REJECTED" },
                { "key": "sort", "value": "newest" }
              ]
            }
          }
        },
        {
          "name": "GET /customer/bookings/:id",
          "request": {
            "method": "GET",
            "header": [{ "key": "Authorization", "value": "Bearer {{customerAccessToken}}" }],
            "url": {
              "raw": "{{baseUrl}}/customer/bookings/{{bookingId}}",
              "host": ["{{baseUrl}}"],
              "path": ["customer", "bookings", "{{bookingId}}"]
            }
          }
        },
        {
          "name": "POST /customer/bookings/:id/cancel",
          "request": {
            "method": "POST",
            "header": [
              { "key": "Content-Type", "value": "application/json" },
              { "key": "Authorization", "value": "Bearer {{customerAccessToken}}" }
            ],
            "url": {
              "raw": "{{baseUrl}}/customer/bookings/{{bookingId}}/cancel",
              "host": ["{{baseUrl}}"],
              "path": ["customer", "bookings", "{{bookingId}}", "cancel"]
            },
            "body": {
              "mode": "raw",
              "raw": "{\n  \"reason\": \"no longer needed\"\n}"
            },
            "description": "Allowed ONLY while status=PENDING. Once an SP has accepted (APPROVED), the customer must contact admin/SP — the dispute flow lands in Sprint 4."
          }
        }
      ]
    },
    {
      "name": "11 — Service Provider Bookings (FRD §2.2 + §2.3)",
      "item": [
        {
          "name": "GET /service-provider/bookings/pool (PENDING open pool)",
          "request": {
            "method": "GET",
            "header": [{ "key": "Authorization", "value": "Bearer {{spAccessToken}}" }],
            "url": {
              "raw": "{{baseUrl}}/service-provider/bookings/pool?page=1&limit=20&sort=oldestFirst",
              "host": ["{{baseUrl}}"],
              "path": ["service-provider", "bookings", "pool"],
              "query": [
                { "key": "page", "value": "1" },
                { "key": "limit", "value": "20" },
                { "key": "serviceId", "value": "", "disabled": true },
                { "key": "sort", "value": "oldestFirst" }
              ]
            },
            "description": "Requires the SP to be `isVerified=true` (admin-approved KYC). Returns 403 otherwise."
          }
        },
        {
          "name": "POST /service-provider/bookings/:id/accept",
          "request": {
            "method": "POST",
            "header": [{ "key": "Authorization", "value": "Bearer {{spAccessToken}}" }],
            "url": {
              "raw": "{{baseUrl}}/service-provider/bookings/{{bookingId}}/accept",
              "host": ["{{baseUrl}}"],
              "path": ["service-provider", "bookings", "{{bookingId}}", "accept"]
            },
            "description": "Atomic claim: only one SP wins per booking. Locks commissionRate + commissionAmount at this moment (admin can't retroactively change them). Returns 409 if booking is already taken or no longer PENDING."
          }
        },
        {
          "name": "GET /service-provider/bookings (my assigned)",
          "request": {
            "method": "GET",
            "header": [{ "key": "Authorization", "value": "Bearer {{spAccessToken}}" }],
            "url": {
              "raw": "{{baseUrl}}/service-provider/bookings?page=1&limit=20&sort=newest",
              "host": ["{{baseUrl}}"],
              "path": ["service-provider", "bookings"],
              "query": [
                { "key": "page", "value": "1" },
                { "key": "limit", "value": "20" },
                { "key": "status", "value": "APPROVED", "disabled": true },
                { "key": "sort", "value": "newest" }
              ]
            }
          }
        },
        {
          "name": "POST /service-provider/bookings/:id/start (APPROVED → IN_PROGRESS)",
          "request": {
            "method": "POST",
            "header": [{ "key": "Authorization", "value": "Bearer {{spAccessToken}}" }],
            "url": {
              "raw": "{{baseUrl}}/service-provider/bookings/{{bookingId}}/start",
              "host": ["{{baseUrl}}"],
              "path": ["service-provider", "bookings", "{{bookingId}}", "start"]
            }
          }
        },
        {
          "name": "POST /service-provider/bookings/:id/complete (IN_PROGRESS → COMPLETED)",
          "request": {
            "method": "POST",
            "header": [{ "key": "Authorization", "value": "Bearer {{spAccessToken}}" }],
            "url": {
              "raw": "{{baseUrl}}/service-provider/bookings/{{bookingId}}/complete",
              "host": ["{{baseUrl}}"],
              "path": ["service-provider", "bookings", "{{bookingId}}", "complete"]
            },
            "description": "For CASH bookings, completion also flips paymentStatus to PAID (paid in cash on delivery). WALLET / ONLINE flows mark PAID at charge time instead — Sprint 4."
          }
        }
      ]
    },
    {
      "name": "12 — Admin Bookings (FRD §3.3)",
      "item": [
        {
          "name": "GET /admin/bookings (all + filters)",
          "request": {
            "method": "GET",
            "header": [{ "key": "Authorization", "value": "Bearer {{adminAccessToken}}" }],
            "url": {
              "raw": "{{baseUrl}}/admin/bookings?page=1&limit=20&sort=newest",
              "host": ["{{baseUrl}}"],
              "path": ["admin", "bookings"],
              "query": [
                { "key": "page", "value": "1" },
                { "key": "limit", "value": "20" },
                { "key": "status", "value": "", "disabled": true },
                { "key": "serviceId", "value": "", "disabled": true },
                { "key": "customerId", "value": "", "disabled": true },
                { "key": "assignedSpId", "value": "", "disabled": true },
                { "key": "paymentMethod", "value": "", "disabled": true },
                { "key": "paymentStatus", "value": "", "disabled": true },
                { "key": "sort", "value": "newest" }
              ]
            }
          }
        },
        {
          "name": "GET /admin/bookings/:id",
          "request": {
            "method": "GET",
            "header": [{ "key": "Authorization", "value": "Bearer {{adminAccessToken}}" }],
            "url": {
              "raw": "{{baseUrl}}/admin/bookings/{{bookingId}}",
              "host": ["{{baseUrl}}"],
              "path": ["admin", "bookings", "{{bookingId}}"]
            }
          }
        }
      ]
    }
  ]
}
